streamframer/__init__.py
streamframer/manager.py
streamframer-0.0.1.dist-info/METADATA
streamframer-0.0.1.dist-info/WHEEL
streamframer-0.0.1.dist-info/licenses/LICENSE
streamframer-0.0.1.dist-info/RECORD
