Metadata-Version: 2.4
Name: streamframer
Version: 0.0.1
Summary: Small framing primitives for byte streams: buffering, delimiter rules, and zero-copy frame views.
Project-URL: Homepage, https://github.com/Kimu754/streamframer
Project-URL: Issues, https://github.com/Kimu754/streamframer/issues
Author: Kerim Takouti
License: MIT License
License-File: LICENSE
Keywords: buffer,framing,protocol,socket,tcp
Classifier: Development Status :: 2 - Pre-Alpha
Classifier: Intended Audience :: Developers
Classifier: License :: OSI Approved :: MIT License
Classifier: Programming Language :: Python :: 3
Classifier: Programming Language :: Python :: 3.9
Classifier: Programming Language :: Python :: 3.10
Classifier: Programming Language :: Python :: 3.11
Classifier: Programming Language :: Python :: 3.12
Classifier: Programming Language :: Python :: 3.13
Classifier: Topic :: Software Development :: Libraries
Classifier: Topic :: System :: Networking
Classifier: Typing :: Typed
Requires-Python: >=3.9
